src/__init__.py
src/dsl/__init__.py
src/dsl/accessrights.py
src/dsl/context copy.py
src/dsl/context.py
src/dsl/datatype.py
src/dsl/exceptions.py
src/dsl/exechelper.py
src/dsl/filemgr.py
src/dsl/fileop.py
src/dsl/grammar.py
src/dsl/graphgen.py
src/dsl/interpreter.py
src/dsl/library.py
src/dsl/parser.py
src/dsl/pygen.py
src/dsl/symtab.py
src/dsl/taskmgr.py
src/dsl/wfobj.py
src/dsl/wftimer.py
tests/__init__.py
tests/dummy_file.py
tests/test_context.py
tests/test_parser.py
tests/wfdsltest.py
wfdsl-0.3.10.dist-info/LICENSE
wfdsl-0.3.10.dist-info/METADATA
wfdsl-0.3.10.dist-info/WHEEL
wfdsl-0.3.10.dist-info/top_level.txt
wfdsl-0.3.10.dist-info/RECORD
