Metadata-Version: 2.1
Name: wfdsl
Version: 0.3.10
Summary: Workflow Domain Specific Language
Home-page: https://github.com/srlabUsask/wfdsl
Author: Muhammad Mainul Hossain
Author-email: Muhammad Mainul Hossain <mainul.hossain@usask.ca>
Project-URL: Homepage, https://github.com/srlabUsask/wfdsl
Project-URL: Issues, https://github.com/srlabUsask/wfdsl/issues
Classifier: Programming Language :: Python :: 3
Classifier: License :: OSI Approved :: MIT License
Classifier: Operating System :: OS Independent
Requires-Python: >=3.6
License-File: LICENSE
